setup.py
harmonicIO/__init__.py
harmonicIO.egg-info/PKG-INFO
harmonicIO.egg-info/SOURCES.txt
harmonicIO.egg-info/dependency_links.txt
harmonicIO.egg-info/entry_points.txt
harmonicIO.egg-info/requires.txt
harmonicIO.egg-info/top_level.txt
harmonicIO/general/__init__.py
harmonicIO/general/colors.py
harmonicIO/general/definition.py
harmonicIO/general/services.py
harmonicIO/master/__init__.py
harmonicIO/master/__main__.py
harmonicIO/master/configuration.py
harmonicIO/master/functions_list.py
harmonicIO/master/messaging_system.py
harmonicIO/master/meta_table.py
harmonicIO/master/rest_service.py
harmonicIO/master/server_socket.py
harmonicIO/stream_connector/__init__.py
harmonicIO/stream_connector/__main__.py
harmonicIO/stream_connector/stream_connector.py
harmonicIO/worker/__init__.py
harmonicIO/worker/__main__.py
harmonicIO/worker/configuration.py
harmonicIO/worker/docker_master.py
harmonicIO/worker/docker_service.py
harmonicIO/worker/rest_service.py