Metadata-Version: 1.0
Name: harmonicIO
Version: 0.3.0
Summary: Lightweight stream processing engine for scientific data
Home-page: UNKNOWN
Author: UNKNOWN
Author-email: UNKNOWN
License: UNKNOWN
Project-URL: homepage, http://haste.research.it.uu.se/
Project-URL: source, https://github.com/HASTE-project/HarmonicIO
Platform: UNKNOWN
